Snorlax/__init__.py
Snorlax/pokemon.csv
Snorlax/random_pokemon.py
YoteelijSnorlax/__init__.py
YoteelijSnorlax/pokemon.csv
YoteelijSnorlax/random_pokemon.py
YoteelijSnorlax-1.0.1.dist-info/METADATA
YoteelijSnorlax-1.0.1.dist-info/WHEEL
YoteelijSnorlax-1.0.1.dist-info/top_level.txt
YoteelijSnorlax-1.0.1.dist-info/RECORD
